{
    "original_request": "TinyLlama/TinyLlama-1.1B-Chat-v1.0",
    "model_id": "TinyLlama/TinyLlama-1.1B-Chat-v1.0",
    "status": "demo",
    "baseline_evaluation": {
        "strategy": {
            "precision": "fp32",
            "prune_ratio": 0.0,
            "expected_memory_multiplier": 1.0,
            "expected_latency_multiplier": 1.0,
            "deployment_mode": "balanced"
        },
        "hardware": "AMD_MI250",
        "simulation": {
            "memory_mb": 4730.0,
            "latency_ms": 756.885391793128,
            "throughput": 1.3212039905155417,
            "energy_kwh": 0.10512297108237888,
            "hardware_fit_score": 100.0,
            "cost_usd": 0.0007358607975766521,
            "score": 0.0,
            "roofline_info": "AI: 255.77 (P), 0.50 (D) | Ridge: 59.84",
            "roofline_telemetry": {
                "bandwidth": 3200000000000.0,
                "compute": 191500000000000.0,
                "ridge": 59.84375,
                "prefill_ai": 255.77132648503797,
                "prefill_perf": 191500000000000.0,
                "decode_ai": 0.4999991269013905,
                "decode_perf": 1599997206084.4495
            },
            "accuracy_penalty": 0.0
        }
    },
    "best_strategy": {
        "precision": "int8",
        "prune_ratio": 0.0,
        "expected_memory_multiplier": 0.25,
        "expected_latency_multiplier": 0.4,
        "deployment_mode": "high_performance"
    },
    "best_evaluation": {
        "strategy": {
            "precision": "int8",
            "prune_ratio": 0.0,
            "expected_memory_multiplier": 0.25,
            "expected_latency_multiplier": 0.4,
            "deployment_mode": "high_performance"
        },
        "hardware": "AMD_MI300X",
        "simulation": {
            "memory_mb": 1374.5,
            "latency_ms": 68.23109233955361,
            "throughput": 14.656074902384338,
            "energy_kwh": 0.011940441159421883,
            "hardware_fit_score": 100.0,
            "cost_usd": 0.00012319502783530512,
            "score": 0.0,
            "roofline_info": "AI: 1020.35 (P), 2.00 (D) | Ridge: 542.53",
            "roofline_telemetry": {
                "bandwidth": 5300000000000.0,
                "compute": 2875400000000000.0,
                "ridge": 542.5283018867924,
                "prefill_ai": 1020.3510022271715,
                "prefill_perf": 2875400000000000.0,
                "decode_ai": 1.9999860304954284,
                "decode_perf": 10599925961625.771
            },
            "accuracy_penalty": 0.1
        },
        "score": 92.8342526694884,
        "scoring_breakdown": {
            "efficiency_score": 92.8342526694884,
            "latency_score": 86.35378153208929,
            "cost_score": 99.99876804972165,
            "energy_score": 99.76119117681156,
            "accuracy_score": 90.0,
            "memory_score": 91.409375,
            "reasoning": "This strategy reduces memory transfer overhead by leveraging lower precision types, shifting the bottleneck towards compute. This achieves significant latency improvements while strictly abiding by your cost and constraint targets."
        },
        "reasoning": "This strategy reduces memory transfer overhead by leveraging lower precision types, shifting the bottleneck towards compute. This achieves significant latency improvements while strictly abiding by your cost and constraint targets."
    },
    "hardware_comparison": [
        {
            "strategy": {
                "precision": "int8",
                "prune_ratio": 0.0,
                "expected_memory_multiplier": 0.25,
                "expected_latency_multiplier": 0.4,
                "deployment_mode": "high_performance"
            },
            "hardware": "AMD_MI300X",
            "simulation": {
                "memory_mb": 1374.5,
                "latency_ms": 68.23109233955361,
                "throughput": 14.656074902384338,
                "energy_kwh": 0.011940441159421883,
                "hardware_fit_score": 100.0,
                "cost_usd": 0.00012319502783530512,
                "score": 0.0,
                "roofline_info": "AI: 1020.35 (P), 2.00 (D) | Ridge: 542.53",
                "roofline_telemetry": {
                    "bandwidth": 5300000000000.0,
                    "compute": 2875400000000000.0,
                    "ridge": 542.5283018867924,
                    "prefill_ai": 1020.3510022271715,
                    "prefill_perf": 2875400000000000.0,
                    "decode_ai": 1.9999860304954284,
                    "decode_perf": 10599925961625.771
                },
                "accuracy_penalty": 0.1
            },
            "score": 92.8342526694884,
            "scoring_breakdown": {
                "efficiency_score": 92.8342526694884,
                "latency_score": 86.35378153208929,
                "cost_score": 99.99876804972165,
                "energy_score": 99.76119117681156,
                "accuracy_score": 90.0,
                "memory_score": 91.409375,
                "reasoning": "This strategy reduces memory transfer overhead by leveraging lower precision types, shifting the bottleneck towards compute. This achieves significant latency improvements while strictly abiding by your cost and constraint targets."
            },
            "reasoning": "This strategy reduces memory transfer overhead by leveraging lower precision types, shifting the bottleneck towards compute. This achieves significant latency improvements while strictly abiding by your cost and constraint targets."
        },
        {
            "strategy": {
                "precision": "int8",
                "prune_ratio": 0.2,
                "expected_memory_multiplier": 0.2,
                "expected_latency_multiplier": 0.36000000000000004,
                "deployment_mode": "high_performance"
            },
            "hardware": "AMD_MI300X",
            "simulation": {
                "memory_mb": 1150.8000000000002,
                "latency_ms": 56.794430457006484,
                "throughput": 17.60736029841874,
                "energy_kwh": 0.009939025329976134,
                "hardware_fit_score": 100.0,
                "cost_usd": 0.0001025454994362617,
                "score": 0.0,
                "roofline_info": "AI: 1146.87 (P), 2.25 (D) | Ridge: 542.53",
                "roofline_telemetry": {
                    "bandwidth": 5300000000000.0,
                    "compute": 2875400000000000.0,
                    "ridge": 542.5283018867924,
                    "prefill_ai": 1146.8731642189584,
                    "prefill_perf": 2875400000000000.0,
                    "decode_ai": 2.2499803554184994,
                    "decode_perf": 11924895883718.047
                },
                "accuracy_penalty": 0.15000000000000002
            },
            "score": 92.69175631016088,
            "scoring_breakdown": {
                "efficiency_score": 92.69175631016088,
                "latency_score": 88.6411139085987,
                "cost_score": 99.99897454500564,
                "energy_score": 99.80121949340047,
                "accuracy_score": 85.0,
                "memory_score": 92.8075
            }
        },
        {
            "strategy": {
                "precision": "fp16",
                "prune_ratio": 0.2,
                "expected_memory_multiplier": 0.4,
                "expected_latency_multiplier": 0.54,
                "deployment_mode": "high_performance"
            },
            "hardware": "AMD_MI300X",
            "simulation": {
                "memory_mb": 2045.6000000000001,
                "latency_ms": 113.58836709407034,
                "throughput": 8.803718422783835,
                "energy_kwh": 0.019877964241462306,
                "hardware_fit_score": 100.0,
                "cost_usd": 0.00020509010725318255,
                "score": 0.0,
                "roofline_info": "AI: 574.72 (P), 1.12 (D) | Ridge: 271.26",
                "roofline_telemetry": {
                    "bandwidth": 5300000000000.0,
                    "compute": 1437700000000000.0,
                    "ridge": 271.2641509433962,
                    "prefill_ai": 574.7154326494201,
                    "prefill_perf": 1437700000000000.0,
                    "decode_ai": 1.1249950888331852,
                    "decode_perf": 5962473970815.882
                },
                "accuracy_penalty": 0.05
            },
            "score": 90.70353757235759,
            "scoring_breakdown": {
                "efficiency_score": 90.70353757235759,
                "latency_score": 77.28232658118593,
                "cost_score": 99.99794909892746,
                "energy_score": 99.60244071517076,
                "accuracy_score": 95.0,
                "memory_score": 87.215
            }
        },
        {
            "strategy": {
                "precision": "int4",
                "prune_ratio": 0.0,
                "expected_memory_multiplier": 0.125,
                "expected_latency_multiplier": 0.3,
                "deployment_mode": "high_performance"
            },
            "hardware": "AMD_MI300X",
            "simulation": {
                "memory_mb": 815.25,
                "latency_ms": 34.115783583210764,
                "throughput": 29.31194582006099,
                "energy_kwh": 0.005970262127061882,
                "hardware_fit_score": 100.0,
                "cost_usd": 6.159794258079721e-05,
                "score": 0.0,
                "roofline_info": "AI: 2033.46 (P), 4.00 (D) | Ridge: 1085.06",
                "roofline_telemetry": {
                    "bandwidth": 5300000000000.0,
                    "compute": 5750800000000000.0,
                    "ridge": 1085.0566037735848,
                    "prefill_ai": 2033.4558366622282,
                    "prefill_perf": 5750800000000000.0,
                    "decode_ai": 3.999944122372005,
                    "decode_perf": 21199703848571.63
                },
                "accuracy_penalty": 0.35
            },
            "score": 90.2571143385731,
            "scoring_breakdown": {
                "efficiency_score": 90.2571143385731,
                "latency_score": 93.17684328335784,
                "cost_score": 99.99938402057418,
                "energy_score": 99.88059475745877,
                "accuracy_score": 65.0,
                "memory_score": 94.9046875
            }
        },
        {
            "strategy": {
                "precision": "int8",
                "prune_ratio": 0.6,
                "expected_memory_multiplier": 0.1,
                "expected_latency_multiplier": 0.27999999999999997,
                "deployment_mode": "high_performance"
            },
            "hardware": "AMD_MI300X",
            "simulation": {
                "memory_mb": 703.4000000000001,
                "latency_ms": 37.22034832159346,
                "throughput": 26.86702422448443,
                "energy_kwh": 0.006513560956278855,
                "hardware_fit_score": 100.0,
                "cost_usd": 6.720340669176598e-05,
                "score": 0.0,
                "roofline_info": "AI: 1776.12 (P), 3.50 (D) | Ridge: 542.53",
                "roofline_telemetry": {
                    "bandwidth": 5300000000000.0,
                    "compute": 2875400000000000.0,
                    "ridge": 542.5283018867924,
                    "prefill_ai": 1776.1205139565793,
                    "prefill_perf": 2875400000000000.0,
                    "decode_ai": 3.4999388840578187,
                    "decode_perf": 18549676085506.438
                },
                "accuracy_penalty": 0.35
            },
            "score": 90.2400574942381,
            "scoring_breakdown": {
                "efficiency_score": 90.2400574942381,
                "latency_score": 92.5559303356813,
                "cost_score": 99.99932796593308,
                "energy_score": 99.86972878087442,
                "accuracy_score": 65.0,
                "memory_score": 95.60375
            }
        },
        {
            "strategy": {
                "precision": "fp16",
                "prune_ratio": 0.0,
                "expected_memory_multiplier": 0.5,
                "expected_latency_multiplier": 0.6,
                "deployment_mode": "high_performance"
            },
            "hardware": "AMD_MI300X",
            "simulation": {
                "memory_mb": 2493.0,
                "latency_ms": 136.46170985223932,
                "throughput": 7.328062949546796,
                "energy_kwh": 0.02388079922414188,
                "hardware_fit_score": 100.0,
                "cost_usd": 0.00024638919834432096,
                "score": 0.0,
                "roofline_info": "AI: 511.09 (P), 1.00 (D) | Ridge: 271.26",
                "roofline_telemetry": {
                    "bandwidth": 5300000000000.0,
                    "compute": 1437700000000000.0,
                    "ridge": 271.2641509433962,
                    "prefill_ai": 511.08612226684517,
                    "prefill_perf": 1437700000000000.0,
                    "decode_ai": 0.9999965076116604,
                    "decode_perf": 5299981490341.8
                },
                "accuracy_penalty": 0.0
            },
            "score": 89.98852933131892,
            "scoring_breakdown": {
                "efficiency_score": 89.98852933131892,
                "latency_score": 72.70765802955214,
                "cost_score": 99.99753610801656,
                "energy_score": 99.52238401551716,
                "accuracy_score": 100.0,
                "memory_score": 84.41875
            }
        },
        {
            "strategy": {
                "precision": "int4",
                "prune_ratio": 0.2,
                "expected_memory_multiplier": 0.1,
                "expected_latency_multiplier": 0.27,
                "deployment_mode": "high_performance"
            },
            "hardware": "AMD_MI300X",
            "simulation": {
                "memory_mb": 703.4000000000001,
                "latency_ms": 28.397462138474562,
                "throughput": 35.21441441223513,
                "energy_kwh": 0.004969555874233048,
                "hardware_fit_score": 100.0,
                "cost_usd": 5.127319552780129e-05,
                "score": 0.0,
                "roofline_info": "AI: 2283.58 (P), 4.50 (D) | Ridge: 1085.06",
                "roofline_telemetry": {
                    "bandwidth": 5300000000000.0,
                    "compute": 5750800000000000.0,
                    "ridge": 1085.0566037735848,
                    "prefill_ai": 2283.5835179441733,
                    "prefill_perf": 5750800000000000.0,
                    "decode_ai": 4.499921422360053,
                    "decode_perf": 23849583538508.28
                },
                "accuracy_penalty": 0.39999999999999997
            },
            "score": 89.68586567906252,
            "scoring_breakdown": {
                "efficiency_score": 89.68586567906252,
                "latency_score": 94.32050757230509,
                "cost_score": 99.99948726804472,
                "energy_score": 99.90060888251534,
                "accuracy_score": 60.00000000000001,
                "memory_score": 95.60375
            }
        },
        {
            "strategy": {
                "precision": "int4",
                "prune_ratio": 0.4,
                "expected_memory_multiplier": 0.075,
                "expected_latency_multiplier": 0.24,
                "deployment_mode": "high_performance"
            },
            "hardware": "AMD_MI300X",
            "simulation": {
                "memory_mb": 591.55,
                "latency_ms": 23.773875813918774,
                "throughput": 42.06297735493911,
                "energy_kwh": 0.004160428267435785,
                "hardware_fit_score": 100.0,
                "cost_usd": 4.292505355290889e-05,
                "score": 0.0,
                "roofline_info": "AI: 2698.50 (P), 5.33 (D) | Ridge: 1085.06",
                "roofline_telemetry": {
                    "bandwidth": 5300000000000.0,
                    "compute": 5750800000000000.0,
                    "ridge": 1085.0566037735848,
                    "prefill_ai": 2698.498601089678,
                    "prefill_perf": 5750800000000000.0,
                    "decode_ai": 5.333209161983079,
                    "decode_perf": 28266008558510.316
                },
                "accuracy_penalty": 0.6
            },
            "score": 86.05930157439465,
            "scoring_breakdown": {
                "efficiency_score": 86.05930157439465,
                "latency_score": 95.24522483721624,
                "cost_score": 99.99957074946447,
                "energy_score": 99.91679143465129,
                "accuracy_score": 40.0,
                "memory_score": 96.3028125
            }
        }
    ],
    "scoring_breakdown": {
        "efficiency_score": 92.8342526694884,
        "latency_score": 86.35378153208929,
        "cost_score": 99.99876804972165,
        "energy_score": 99.76119117681156,
        "accuracy_score": 90.0,
        "memory_score": 91.409375,
        "reasoning": "This strategy reduces memory transfer overhead by leveraging lower precision types, shifting the bottleneck towards compute. This achieves significant latency improvements while strictly abiding by your cost and constraint targets."
    },
    "workload_type": "chat_inference"
}